scm_python_eclipse/lib/eclipse.py
scm_python_eclipse/lib/eclipse_exercise.py
scm_python_eclipse/tapps/eclipse/eiumCommon.py
scm_python_eclipse/tapps/eclipse/eiumExternalServer.py
scm_python_eclipse/tapps/eclipse/eiumIde.py
scm_python_eclipse/tapps/eclipse/eiumRuntime.py
scm_python_eclipse/tapps/eclipse/eiumType.py
scm_python_eclipse/tapps/eclipse/eiumWebApp.py
scm_python_eclipse/tapps/eclipse/metaFile.py
scm_python_eclipse/tapps/eclipse/workaround.py
scm_python_eclipse/tapps/exercise/lib_webapp.py
scm_python_eclipse-0.1.0.dist-info/METADATA
scm_python_eclipse-0.1.0.dist-info/WHEEL
scm_python_eclipse-0.1.0.dist-info/top_level.txt
scm_python_eclipse-0.1.0.dist-info/RECORD
